ArtexSTT/STT.py
ArtexSTT/__init__.py
ArtexSTT-0.0.1.dist-info/LICENSE
ArtexSTT-0.0.1.dist-info/METADATA
ArtexSTT-0.0.1.dist-info/WHEEL
ArtexSTT-0.0.1.dist-info/top_level.txt
ArtexSTT-0.0.1.dist-info/RECORD
