Metadata-Version: 2.1
Name: ArtexSTT
Version: 0.0.1
Summary: A python speech to text library
Home-page: https://github.com/JunaidParkar/Python-STT
Author: Artex AI
Project-URL: Documentation, https://github.com/JunaidParkar/Python-STT
Project-URL: Source, https://github.com/JunaidParkar/Python-STT
Project-URL: Tracker, https://github.com/JunaidParkar/Python-STT
Classifier: Programming Language :: Python :: 3
Classifier: License :: OSI Approved :: Boost Software License 1.0 (BSL-1.0)
Classifier: Operating System :: OS Independent
Requires-Python: >=3.6
License-File: LICENSE
Requires-Dist: selenium ==4.22.0
Requires-Dist: webdriver-manager ==4.0.1
Requires-Dist: mtranslate ==1.8
Requires-Dist: pathlib ==1.0.1
